coderag/__init__.py
coderag/config.py
coderag/indexer/code_parser.py
coderag/indexer/embedder.py
coderag/indexer/repository.py
coderag/storage/base.py
coderag/storage/chromadb.py
coderag/storage/pinecone.py
coderag/utils/generate_summary.py
coderag-0.1.0.dist-info/LICENSE
coderag-0.1.0.dist-info/METADATA
coderag-0.1.0.dist-info/WHEEL
coderag-0.1.0.dist-info/RECORD
