Metadata-Version: 2.3
Name: coderag
Version: 0.1.0
Summary: A plug and play python package for code repository indexing and semantic search
License: Apache-2.0 License
Author: Mohwit
Author-email: mohwits@gmail.com
Requires-Python: >=3.9
Classifier: Development Status :: 4 - Beta
Classifier: Intended Audience :: Developers
Classifier: Topic :: Software Development :: Libraries
Classifier: License :: OSI Approved :: Apache Software License
Classifier: Programming Language :: Python :: 3
Classifier: Programming Language :: Python :: 3.10
Classifier: Programming Language :: Python :: 3.11
Requires-Dist: anthropic (>=0.49.0,<0.50.0)
Requires-Dist: chromadb (>=0.6.3,<0.7.0)
Requires-Dist: pathlib (>=1.0.1,<2.0.0)
Requires-Dist: pinecone (>=6.0.2,<7.0.0)
Requires-Dist: rerankers (>=0.9.1,<0.10.0)
Requires-Dist: sentence-transformers (>=4.0.1,<5.0.0)
Requires-Dist: tqdm (>=4.67.1,<5.0.0)
Requires-Dist: tree-sitter (>=0.24.0,<0.25.0)
Requires-Dist: tree-sitter-java (>=0.23.5,<0.24.0)
Requires-Dist: tree-sitter-javascript (>=0.23.1,<0.24.0)
Requires-Dist: tree-sitter-python (>=0.23.6,<0.24.0)
Requires-Dist: tree-sitter-typescript (>=0.23.2,<0.24.0)
Project-URL: Bug Tracker, https://github.com/mohwits/coderag/issues
Project-URL: Homepage, https://github.com/mohwits/coderag
